{
	"info": {
		"_postman_id": "db1e98f0-246d-40ee-8fc3-f2fd95c1f4f5",
		"name": "GitHubDemo",
		"schema": "https://schema.getpostman.com/json/collection/v2.1.0/collection.json"
	},
	"item": [
		{
			"name": "http://dummy.restapiexample.com/api/v1/employees",
			"request": {
				"method": "GET",
				"header": [],
				"url": {
					"raw": "http://dummy.restapiexample.com/api/v1/employees",
					"protocol": "http",
					"host": [
						"dummy",
						"restapiexample",
						"com"
					],
					"path": [
						"api",
						"v1",
						"employees"
					]
				}
			},
			"response": []
		}
	]
}